rets/__init__.py
rets/errors.py
rets/client/__init__.py
rets/client/client.py
rets/client/decoder.py
rets/client/object_type.py
rets/client/record.py
rets/client/resource.py
rets/client/resource_class.py
rets/client/utils.py
rets/http/__init__.py
rets/http/client.py
rets/http/data.py
rets/http/parsers/__init__.py
rets/http/parsers/parse.py
rets/http/parsers/parse_object.py
rets_python-0.4.12.dist-info/LICENSE.md
rets_python-0.4.12.dist-info/METADATA
rets_python-0.4.12.dist-info/WHEEL
rets_python-0.4.12.dist-info/top_level.txt
rets_python-0.4.12.dist-info/RECORD
