Metadata-Version: 2.1
Name: rets-python
Version: 0.4.12
Summary: rets-python
Home-page: https://github.com/opendoor-labs/rets
Author: Martin Liu
Author-email: martin@opendoor.com
License: MIT License
Classifier: Intended Audience :: Developers
Classifier: Intended Audience :: Financial and Insurance Industry
Classifier: Intended Audience :: Information Technology
Classifier: Intended Audience :: Other Audience
Classifier: License :: OSI Approved :: MIT License
Classifier: Natural Language :: English
Classifier: Operating System :: OS Independent
Classifier: Programming Language :: Python
Classifier: Programming Language :: Python :: 3
Classifier: Programming Language :: Python :: 3.5
Classifier: Programming Language :: Python :: 3.6
Classifier: Programming Language :: Python :: 3 :: Only
Classifier: Programming Language :: Python :: Implementation :: CPython
Classifier: Programming Language :: Python :: Implementation :: PyPy
Classifier: Topic :: Internet :: WWW/HTTP
Classifier: Topic :: Internet :: WWW/HTTP :: Indexing/Search
License-File: LICENSE.md
Requires-Dist: requests>=2.12.3
Requires-Dist: requests-toolbelt!=0.9.0,>=0.7.0
Requires-Dist: udatetime==0.0.17
Requires-Dist: lxml>=4.3.0
